opentelemetry_wrapper/__init__.py
opentelemetry_wrapper/v0/config/otel_exporter_otlp.py
opentelemetry_wrapper/v0/config/otel_header_attributes.py
opentelemetry_wrapper/v0/config/otel_headers.py
opentelemetry_wrapper/v0/config/otel_log_level.py
opentelemetry_wrapper/v0/config/otel_service_name.py
opentelemetry_wrapper/v0/config/otel_wrapper_prometheus_exporter.py
opentelemetry_wrapper/v0/dependencies/fastapi/fastapi_prometheus.py
opentelemetry_wrapper/v0/dependencies/fastapi/fastapi_typedef.py
opentelemetry_wrapper/v0/dependencies/fastapi/starlette_request_hook.py
opentelemetry_wrapper/v0/dependencies/opentelemetry/instrument_dataclasses.py
opentelemetry_wrapper/v0/dependencies/opentelemetry/instrument_decorator.py
opentelemetry_wrapper/v0/dependencies/opentelemetry/instrument_fastapi.py
opentelemetry_wrapper/v0/dependencies/opentelemetry/instrument_logging.py
opentelemetry_wrapper/v0/dependencies/opentelemetry/instrument_requests.py
opentelemetry_wrapper/v0/dependencies/opentelemetry/instrument_sqlalchemy.py
opentelemetry_wrapper/v0/dependencies/opentelemetry/instrument_system_metrics.py
opentelemetry_wrapper/v0/dependencies/opentelemetry/otel_providers.py
opentelemetry_wrapper/v0/dependencies/opentelemetry/resource_detector.py
opentelemetry_wrapper/v0/dependencies/sqlalchemy/engine_typedef.py
opentelemetry_wrapper/v0/utils/extract_json_header.py
opentelemetry_wrapper/v0/utils/introspect.py
opentelemetry_wrapper/v0/utils/json_encoder.py
opentelemetry_wrapper/v0/utils/logging_json_formatter.py
opentelemetry_wrapper/v0/utils/type_checking.py
opentelemetry_wrapper-0.1.25.dist-info/LICENSE
opentelemetry_wrapper-0.1.25.dist-info/WHEEL
opentelemetry_wrapper-0.1.25.dist-info/METADATA
opentelemetry_wrapper-0.1.25.dist-info/RECORD
