Metadata-Version: 2.1
Name: opentelemetry_wrapper
Version: 0.1.25
Summary: a wrapper around `opentelemetry` and `opentelemetry-instrumentation-*` to make life a bit easier
Author-email: Avery Khoo <averykhoo@gmail.com>
Requires-Python: >3.8.0
Classifier: License :: OSI Approved :: Apache Software License
Requires-Dist: asgiref
Requires-Dist: fastapi
Requires-Dist: itsdangerous
Requires-Dist: opentelemetry-api
Requires-Dist: opentelemetry-exporter-otlp
Requires-Dist: opentelemetry-exporter-prometheus
Requires-Dist: opentelemetry-instrumentation-fastapi
Requires-Dist: opentelemetry-instrumentation-logging
Requires-Dist: opentelemetry-instrumentation-requests
Requires-Dist: opentelemetry-instrumentation-sqlalchemy
Requires-Dist: opentelemetry-instrumentation-system-metrics
Requires-Dist: opentelemetry-sdk
Requires-Dist: pydantic
Requires-Dist: requests
Requires-Dist: sqlalchemy
Requires-Dist: starlette
Requires-Dist: typing-extensions
Requires-Dist: uvicorn
Project-URL: Home, https://github.com/averykhoo/opentelemetry_wrapper
